bmomd/__init__.py
bmomd/lib_abc/__init__.py
bmomd/lib_xyz/__init__.py
bmomd/nannyml/__init__.py
bmomd/nannyml/_typing.py
bmomd/nannyml/analytics.py
bmomd/nannyml/base.py
bmomd/nannyml/calibration.py
bmomd/nannyml/chunk.py
bmomd/nannyml/config.py
bmomd/nannyml/exceptions.py
bmomd/nannyml/runner.py
bmomd/nannyml/usage_logging.py
bmomd/nannyml/cli/__init__.py
bmomd/nannyml/cli/cli.py
bmomd/nannyml/cli/run.py
bmomd/nannyml/datasets/__init__.py
bmomd/nannyml/datasets/datasets.py
bmomd/nannyml/datasets/data/__init__.py
bmomd/nannyml/drift/__init__.py
bmomd/nannyml/drift/ranker.py
bmomd/nannyml/drift/multivariate/__init__.py
bmomd/nannyml/drift/multivariate/data_reconstruction/__init__.py
bmomd/nannyml/drift/multivariate/data_reconstruction/calculator.py
bmomd/nannyml/drift/multivariate/data_reconstruction/result.py
bmomd/nannyml/drift/univariate/__init__.py
bmomd/nannyml/drift/univariate/calculator.py
bmomd/nannyml/drift/univariate/methods.py
bmomd/nannyml/drift/univariate/result.py
bmomd/nannyml/io/__init__.py
bmomd/nannyml/io/base.py
bmomd/nannyml/io/file_reader.py
bmomd/nannyml/io/file_writer.py
bmomd/nannyml/io/pickle_file_writer.py
bmomd/nannyml/io/raw_files_writer.py
bmomd/nannyml/io/db/__init__.py
bmomd/nannyml/io/db/database_writer.py
bmomd/nannyml/io/db/entities.py
bmomd/nannyml/io/db/mappers.py
bmomd/nannyml/io/store/__init__.py
bmomd/nannyml/io/store/base.py
bmomd/nannyml/io/store/file_store.py
bmomd/nannyml/io/store/serializers.py
bmomd/nannyml/performance_calculation/__init__.py
bmomd/nannyml/performance_calculation/calculator.py
bmomd/nannyml/performance_calculation/result.py
bmomd/nannyml/performance_calculation/metrics/__init__.py
bmomd/nannyml/performance_calculation/metrics/base.py
bmomd/nannyml/performance_calculation/metrics/binary_classification.py
bmomd/nannyml/performance_calculation/metrics/multiclass_classification.py
bmomd/nannyml/performance_calculation/metrics/regression.py
bmomd/nannyml/performance_estimation/__init__.py
bmomd-0.0.8.dist-info/LICENSE
bmomd-0.0.8.dist-info/METADATA
bmomd-0.0.8.dist-info/WHEEL
bmomd-0.0.8.dist-info/top_level.txt
bmomd-0.0.8.dist-info/RECORD
