Metadata-Version: 2.1
Name: bmomd
Version: 0.0.8
Summary: experimental libraries
Home-page: 
Author: ramenz
Author-email: ramenz@juno.com
Classifier: Programming Language :: Python :: 3
Classifier: License :: OSI Approved :: MIT License
Classifier: Operating System :: OS Independent
License-File: LICENSE
